gogoanime/__init__.py
gogoanime/__main__.py
gogoanime/anime_info.py
gogoanime/constants.py
gogoanime/download.py
gogoanime/get_download_url.py
gogoanime/login.py
gogoanime/user.py
gogoanime_anitaku-0.0.2.dist-info/LICENSE
gogoanime_anitaku-0.0.2.dist-info/METADATA
gogoanime_anitaku-0.0.2.dist-info/WHEEL
gogoanime_anitaku-0.0.2.dist-info/entry_points.txt
gogoanime_anitaku-0.0.2.dist-info/top_level.txt
gogoanime_anitaku-0.0.2.dist-info/RECORD
