Metadata-Version: 2.2
Name: gogoanime-anitaku
Version: 0.0.2
Summary: Download anime from gogoanime website.
Author-email: HSAkash <hemelakash472@gmail.com>
License: MIT License
Project-URL: Homepage, https://github.com/HSAkash/gogoanime
Project-URL: documentation, https://github.com/HSAkash/gogoanime/wiki
Project-URL: changelog, https://github.com/HSAkash/gogoanime/releases
Project-URL: bug_tracker, https://github.com/HSAkash/gogoanime/issues
Keywords: gogoanime,anime
Classifier: Programming Language :: Python :: 3.7
Classifier: Programming Language :: Python :: 3.8
Classifier: Programming Language :: Python :: 3.9
Classifier: Programming Language :: Python :: 3.10
Classifier: Programming Language :: Python :: 3.11
Classifier: Programming Language :: Python :: 3.12
Classifier: Programming Language :: Python :: 3 :: Only
Requires-Python: >=3.7
License-File: LICENSE
Requires-Dist: tqdm
Requires-Dist: aria2
Requires-Dist: bs4
Requires-Dist: requests
Requires-Dist: click
Requires-Dist: rich
Requires-Dist: keyring
Provides-Extra: cli-enhanced
Requires-Dist: rich; extra == "cli-enhanced"
Provides-Extra: testing
Requires-Dist: pytest; extra == "testing"
Requires-Dist: pytest-cov; extra == "testing"
Requires-Dist: tox; extra == "testing"
